unmass/__init__.py
unmass/exp.py
unmass/filter_noisy_data.py
unmass/fp16.py
unmass/logger.py
unmass/preprocess.py
unmass/slurm.py
unmass/train.py
unmass/trainer.py
unmass/translate.py
unmass/translate_ensemble.py
unmass/utils.py
unmass/data/__init__.py
unmass/data/dataset.py
unmass/data/dictionary.py
unmass/data/loader.py
unmass/evaluation/__init__.py
unmass/evaluation/evaluator.py
unmass/model/__init__.py
unmass/model/transformer.py
unmass-0.1.0.data/scripts/unmass-prep
unmass-0.1.0.dist-info/LICENSE-MASS.txt
unmass-0.1.0.dist-info/LICENSE-XLM.txt
unmass-0.1.0.dist-info/METADATA
unmass-0.1.0.dist-info/WHEEL
unmass-0.1.0.dist-info/entry_points.txt
unmass-0.1.0.dist-info/top_level.txt
unmass-0.1.0.dist-info/RECORD
