Metadata-Version: 2.1
Name: unmass
Version: 0.1.0
Summary: UNMASS - Unsupervised NMT with Masked Sequence-to-Sequence training
Home-page: https://github.com/thammegowda/unmass
Author: Thamme Gowda
Author-email: tgowdan@gmail.com
License: UNKNOWN
Platform: any
Classifier: Programming Language :: Python :: 3.7
Classifier: License :: OSI Approved :: MIT License
Classifier: Operating System :: OS Independent
Classifier: Intended Audience :: Science/Research
Classifier: Topic :: Scientific/Engineering :: Artificial Intelligence
Requires-Python: >=3.7
Requires-Dist: ruamel.yaml (>=0.16.10)
Requires-Dist: sacrebleu (>=1.4.6)
Requires-Dist: sacremoses (>=0.0.43)
Requires-Dist: nlcodec (>=0.2.3)
Requires-Dist: torch (>=1.4)
